pisim/__init__.py
pisim/dataLoadStore/__init__.py
pisim/dataLoadStore/common.py
pisim/dataLoadStore/dipendente.py
pisim/dataLoadStore/factoryDescs.py
pisim/dataLoadStore/inflazione.py
pisim/dataLoadStore/pensione.py
pisim/dataLoadStore/salario.py
pisim/dataLoadStore/fondoPensione/__init__.py
pisim/dataLoadStore/fondoPensione/accumulo.py
pisim/dataLoadStore/fondoPensione/base.py
pisim/dataLoadStore/fondoPensione/rendita.py
pisim/dataLoadStore/reports/__init__.py
pisim/dataLoadStore/reports/common.py
pisim/dataLoadStore/reports/dipendente.py
pisim/dataLoadStore/reports/fpAccumulo.py
pisim/dataLoadStore/reports/fpBase.py
pisim/dataLoadStore/reports/fpRendita.py
pisim/dataLoadStore/reports/inflazione.py
pisim/dataLoadStore/reports/pensione.py
pisim/dataLoadStore/reports/reports.py
pisim/dataLoadStore/reports/results.py
pisim/dataLoadStore/reports/salario.py
pisim/engine/__init__.py
pisim/engine/common.py
pisim/engine/errors.py
pisim/engine/fondoPensione.py
pisim/engine/report.py
pisim/engine/serieStoriche.py
pisim/engine/tfr.py
pisim/gui/__init__.py
pisim/gui/app.py
pisim/gui/commonEntry.py
pisim/gui/resultsCommon.py
pisim/gui/resultsWindow.py
pisim/gui/settingsWindow.py
pisim/gui/signals.py
pisim/gui/infoWindows/__init__.py
pisim/gui/infoWindows/baseInfoWin.py
pisim/gui/infoWindows/dipendenteInfoWin.py
pisim/gui/infoWindows/fpAccumuloInfoWin.py
pisim/gui/infoWindows/fpBaseInfoWin.py
pisim/gui/infoWindows/fpRenditaInfoWin.py
pisim/gui/infoWindows/inflazioneInfoWin.py
pisim/gui/infoWindows/mainWinInfoWin.py
pisim/gui/infoWindows/pensioneInfoWin.py
pisim/gui/infoWindows/risultatiInfoWin.py
pisim/gui/infoWindows/salarioInfoWin.py
pisim/gui/mainWinPanes/__init__.py
pisim/gui/mainWinPanes/basePane.py
pisim/gui/mainWinPanes/dipendentePane.py
pisim/gui/mainWinPanes/fpAccumuloPane.py
pisim/gui/mainWinPanes/fpBasePane.py
pisim/gui/mainWinPanes/fpRenditaPane.py
pisim/gui/mainWinPanes/inflazionePane.py
pisim-1.0b3.dist-info/DESCRIPTION.rst
pisim-1.0b3.dist-info/METADATA
pisim-1.0b3.dist-info/RECORD
pisim-1.0b3.dist-info/WHEEL
pisim-1.0b3.dist-info/entry_points.txt
pisim-1.0b3.dist-info/metadata.json
pisim-1.0b3.dist-info/top_level.txt
