Metadata-Version: 2.0
Name: pisim
Version: 1.0b3
Summary: A Supplementary Pension Simulator for Italy
Home-page: https://pypi.org/project/pisim/
Author: Luca Casone
Author-email: csnluca@gmail.com
License: MIT
Platform: UNKNOWN
Classifier: Development Status :: 4 - Beta
Classifier: Intended Audience :: Financial and Insurance Industry
Classifier: Topic :: Utilities
Classifier: License :: OSI Approved :: MIT License
Classifier: Programming Language :: Python :: 2.7
Requires-Python: >=2.7, !=3.*, !=4.*
Requires-Dist: appdirs
Requires-Dist: numpy
